{
  "playerName": "",
  "playerDescription": "",
  "stats": {
    "might": {
      "pool": null,
      "maxPool": null,
      "edge": null
    },
    "speed": {
      "pool": null,
      "maxPool": null,
      "edge": null
    },
    "intellect ": {
      "pool": null,
      "maxPool": null,
      "edge": null
    }
  },
  "Effort": null,
  "teir": null,
  "xp": null,
  "Descriptor ": "",
  "type": "",
  "focus": "",
  "specialAbilities ": [
    {
      "name": "",
      "statType": "",
      "cost": null
    },
    {
      "name": "",
      "statType": "",
      "cost": null
    }
  ],
  "skills": [
    {
      "name": "",
      "trained": false,
      "specialized": false,
      "disability ": false
    },
    {
      "name": "",
      "trained": false,
      "specialized": false,
      "disability ": false
    },
    {
      "name": "",
      "trained": false,
      "specialized": false,
      "disability ": false
    }
  ],
  "items": [
    {
      "name": "",
      "range": "",
      "damage": null,
      "durability ": "",
      "description ": ""
    },
    {
      "name": "",
      "range": "",
      "damage": null,
      "durability ": "",
      "description ": ""
    }
  ],
  "cypher": [
    {
      "name": "",
      "effect": "",
      "subtle ": false,
      "manifest": false,
      "level": null
    }
  ]
}